pyengnet/Dataset.py
pyengnet/Engnet.py
pyengnet/File.py
pyengnet/Kendall.py
pyengnet/NMI.py
pyengnet/Normalization.py
pyengnet/Spearman.py
pyengnet/__init__.py
pyengnet/version.py
pyengnet-0.0.3.dist-info/LICENSE
pyengnet-0.0.3.dist-info/METADATA
pyengnet-0.0.3.dist-info/WHEEL
pyengnet-0.0.3.dist-info/top_level.txt
pyengnet-0.0.3.dist-info/RECORD
