Metadata-Version: 2.1
Name: pyengnet
Version: 0.0.3
Summary: pyEnGNet: optimized reconstruction of gene co-expression networks using multi-GPU
Author: Aurelio Lopez-Fernandez
Author-email: alopfer1@upo.es
Keywords: python,multiGPU,bioinformatics,gene networks
Classifier: Programming Language :: Python :: 3
Classifier: License :: OSI Approved :: MIT License
Classifier: Operating System :: OS Independent
Classifier: Intended Audience :: Science/Research
Classifier: Topic :: Scientific/Engineering
Requires-Python: >=3.9
License-File: LICENSE
Requires-Dist: numpy
Requires-Dist: tqdm
Requires-Dist: multiprocess
Requires-Dist: pandas
Requires-Dist: matplotlib
Requires-Dist: networkx
Requires-Dist: scipy
